sessions/abb24f956f59c4c5c558a94f65cd628b53f3bd95a7ea98.74395612/uploader_dut.v
module updown_counter(clk, reset, mode, count);
	input clk, reset, mode;
	output [ 7 :0 ] count;
wire reset, mode;
reg [ 7 :0] count;
	
always @(posedge clk )
begin
		 if(!reset)
	count <= 8'b0100;
		 else if (mode == 0)
count <= count + 1;
	else if (mode == 1)
		count <= count - 1;
end
endmodule

docs/Expt1_bidirectional_counter/updown_counter.1346073915.vcd
$date August 27 2012 16:25:15 $end
$version Virtual Lab: FPGA Automation Ver 0.9 $end
$timescale 1 ns $end
$scope module updown_counter $end
$var wire 1 ! clk $end
$var wire 1 @ reset $end
$var wire 1 # mode $end
$var wire 8 $ count[7:0] $end
$upscope  $end
$enddefinitions  $end
$comment 
Note: VCD Generated from Input and Output Signals from the FPGA
 $end
#0
1!
0@
0#
b00000000 $
#1
0!
#2
1!
b00000100 $
#3
0!
#4
1!
#5
0!
#6
1!
#7
0!
#8
1!
#9
0!
#10
1!
1@
#11
0!
#12
1!
b00000101 $
#13
0!
#14
1!
b00000110 $
#15
0!
#16
1!
b00000111 $
#17
0!
#18
1!
b00001000 $
#19
0!
#20
1!
b00001001 $
#21
0!
#22
1!
1#
b00001010 $
#23
0!
#24
1!
b00001001 $
#25
0!
#26
1!
b00001000 $
#27
0!
#28
1!
b00000111 $
#29
0!
#30
1!
b00000110 $
#31
0!
#32
1!
b00000101 $
#33
0!
#34
1!
0@
b00000100 $
