docs/Expt3/tlc.v
module tlc ( clk, reset,  vehicle_sensor, highway_signal, farm_signal );
  input reset, clk, vehicle_sensor; 
  output [1:0] highway_signal, farm_signal;
  parameter HG=2'b00, HY=2'b01, FG=2'b10, FY=2'b11;
  parameter GREEN = 2'b00, YELLOW = 2'b01, RED = 2'b10;
  reg [1:0] highway_signal, farm_signal, cur_state, next_state;
  reg [1:0] highway_signal1, farm_signal1;
  reg reset_timer; reg [3:0] timer; wire long_timeout, short_timeout;
  always @( negedge clk or negedge reset ) 
    if (reset == 1'b0) 
		cur_state <= HG; 
	 else
	  cur_state <= next_state;
  
   always @( negedge clk or negedge reset )
    if (reset == 1'b0) 
			timer <= 4'h0;
	 else if ( reset_timer == 1'b1 ) 
			timer <= 4'h0; 
    else if ( timer == 4'hf ) 
			timer <= 4'b1111;
    else 
			timer <= (timer + 1) % 16;
			
  assign short_timeout = timer[0] ;  
  assign long_timeout = ( (timer[1]==1) || (timer[2]==1) || (timer[3]==1) ) ? 1'b1 : 1'b0;
  
  
  always @(cur_state or long_timeout or vehicle_sensor or short_timeout) 
  begin
       
    if (cur_state == HG)
			begin
	       highway_signal <= GREEN; farm_signal <= RED;
    
			 if (vehicle_sensor == 1'b1 && long_timeout == 1'b1 )
				begin
						next_state <= HY;reset_timer <= 1'b1;
				end
			 else 
				begin
					next_state <= HG;reset_timer <= 1'b0;
				end
			end					
			
	 else if (cur_state == HY) 
			 begin 
				highway_signal <= YELLOW; farm_signal <= RED;
				if ( short_timeout == 1'b1 ) 
				begin 
					next_state <= FG; reset_timer <= 1'b1;
				end 
				else  
				begin  
					next_state <= HY;reset_timer <= 1'b0; 
				end
			 end 
	 else if (cur_state == FG) 
			 begin 
				highway_signal <= RED; farm_signal <= GREEN;
				if ( long_timeout == 1'b1 ) 
					begin 
					  reset_timer<= 1'b1;
					  //if ( short_timeout == 1'b1 ) begin
						next_state <= FY;//end
					end 
				else  
					begin  
						next_state <= FG;  reset_timer<= 1'b0;
					end
				end 
	else if (cur_state == FY) 
			begin 
				highway_signal <= RED; farm_signal <= YELLOW;
				if ( short_timeout == 1'b1 ) 
					begin 
						next_state <= HG; reset_timer<= 1'b1;
					end 
				else  
					begin  
					next_state <= FY; reset_timer<= 1'b0; 
					end
			 end 
	else  
			begin 
			 highway_signal <= RED; farm_signal <= RED;
			 next_state <= HG;reset_timer <= 1'b1; 
			end
  end // always
endmodule

docs/Expt3/tlc.1346407362.vcd
$date August 31 2012 13:02:42 $end
$version Virtual Lab: FPGA Automation Ver 0.9 $end
$timescale 1 ns $end
$scope module tlc $end
$var wire 1 ! clk $end
$var wire 1 @ reset $end
$var wire 1 # vehicle_sensor $end
$var wire 2 $ highway_signal[1:0] $end
$var wire 2 % farm_signal[1:0] $end
$upscope  $end
$enddefinitions  $end
$comment 
Note: VCD Generated from Input and Output Signals from the FPGA
 $end
#0
1!
0@
0#
b00 $
b00 %
#1
0!
#2
1!
1@
b10 %
#3
0!
#4
1!
#5
0!
#6
1!
#7
0!
#8
1!
#9
0!
#10
1!
#11
0!
#12
1!
#13
0!
#14
1!
1#
b01 $
#15
0!
#16
1!
#17
0!
#18
1!
b10 $
b00 %
#19
0!
#20
1!
#21
0!
#22
1!
#23
0!
#24
1!
b01 %
#25
0!
#26
1!
#27
0!
#28
1!
0#
b00 $
b10 %
#29
0!
#30
1!
#31
0!
#32
1!
#33
0!
#34
1!
#35
0!
#36
1!
#37
0!
#38
1!
#39
0!
#40
1!
#41
0!
#42
1!
#43
0!
#44
1!
#45
0!
#46
1!
#47
0!
#48
1!
#49
0!
#50
1!
1#
b01 $
#51
0!
#52
1!
0@
b00 $
